FSV/Calculator.py
FSV/Combine_fig_MS.py
FSV/Combine_fig_ppt.py
FSV/Combine_method_SI.py
FSV/Combine_multi_conf.py
FSV/Molecule.py
FSV/Results.py
FSV/Strain_energy.py
FSV/__init__.py
FSV/atompair.py
FSV/autofragment.py
FSV/basis_functions.py
FSV/fragmentation.py
FSV/inputs.py
FSV/multi_mov.py
FSV/pml_str.py
FSV/write_run_pml.py
FSV/lib/ONIOM_Cscale.txt
FSV/lib/ONIOM_Hscale.txt
FSV/lib/ONIOM_Nscale.txt
FSV/lib/ONIOM_Oscale.txt
OBSV/Calculator.py
OBSV/Molecule.py
OBSV/Results.py
OBSV/Strain_energy.py
OBSV/__init__.py
OBSV/basis_functions.py
OBSV/fragmentation.py
OBSV/inputs.py
OBSV/lib/ONIOM_Cscale.txt
OBSV/lib/ONIOM_Hscale.txt
OBSV/lib/ONIOM_Nscale.txt
OBSV/lib/ONIOM_Oscale.txt
FSV-1.0.12.dist-info/METADATA
FSV-1.0.12.dist-info/WHEEL
FSV-1.0.12.dist-info/entry_points.txt
FSV-1.0.12.dist-info/top_level.txt
FSV-1.0.12.dist-info/RECORD
