Metadata-Version: 2.1
Name: FSV
Version: 1.0.12
Summary: Fragmentation-based Strain Visualisation 
Home-page: 
Author-email: yanzy@sustech.edu.cn
Requires-Python: ~=3.9
